{
    "request": {
        "domain_name": "mertz11.com",
        "is_subdomain": false,
        "domain_enabled": true,
        "domain_description": "Created via Factory during tests",
        "reseller_reference_code": "Code01",
        "settings": [
            {
                "domain_setting_category": "domain",
                "domain_setting_subcategory": "language",
                "domain_setting_name": "code",
                "domain_setting_value": "uk-ua",
                "domain_setting_order": 0,
                "domain_setting_enabled": true,
                "domain_setting_description": "Est voluptates sit ab ex voluptatem. Deleniti totam quia velit minima sequi expedita maxime. Voluptatum ad architecto ut fugiat nihil accusamus sit. Ut sed est quia qui quod placeat."
            },
            {
                "domain_setting_category": "voicemail",
                "domain_setting_subcategory": "message_order",
                "domain_setting_name": "text",
                "domain_setting_value": "desc",
                "domain_setting_order": 1,
                "domain_setting_enabled": true,
                "domain_setting_description": "Play oldest voicemail first"
            }
        ],
        "users": [
            {
                "is_admin": true,
                "reseller_reference_code": "Code01",
                "username": "alyson.dietrich2@howe.com",
                "password": "7A%XQ>*k2?XPSYL1K4",
                "user_email": "alyson.dietrich@howe.com",
                "contacts": [
                    {
                        "contact_type": "customer",
                        "contact_organization": "Littel Inc",
                        "contact_name_prefix": "Prof.",
                        "contact_name_given": "Emilio",
                        "contact_name_middle": "A.",
                        "contact_name_family": "Frami",
                        "contact_name_suffix": "Jr.",
                        "contact_nickname": "muller.donnie",
                        "contact_title": "Ms.",
                        "contact_role": "Online Marketing Analyst",
                        "contact_category": "Contacts added via API",
                        "contact_url": "http://www.hermann.info/molestias-minus-voluptas-harum-reiciendis",
                        "contact_time_zone": "America/Los_Angeles",
                        "contact_note": "Quo veritatis magnam hic rerum culpa facilis sint explicabo. Voluptas et aut magni adipisci nulla et. Exercitationem optio reprehenderit voluptatem dolore excepturi et."
                    },
                    {
                        "contact_type": "supplier",
                        "contact_organization": "Kub PLC",
                        "contact_name_prefix": "Prof.",
                        "contact_name_given": "Patricia",
                        "contact_name_middle": "A.",
                        "contact_name_family": "Mohr",
                        "contact_name_suffix": "DVM",
                        "contact_nickname": "kautzer.cordie",
                        "contact_title": "Prof.",
                        "contact_role": "Administrative Services Manager",
                        "contact_category": "Contacts added via API",
                        "contact_url": "http://www.rogahn.com/est-voluptate-ut-velit-aut-non-ut.html",
                        "contact_time_zone": "Africa/Kinshasa",
                        "contact_note": "Quis placeat labore hic reiciendis omnis enim corporis. Fugit beatae repellendus amet commodi id odit sequi inventore. Praesentium est et harum et voluptatem. Sint maxime deserunt laboriosam harum."
                    }
                ],
                "extensions": [
                    {
                        "directory_visible": "false",
                        "directory_exten_visible": "true",
                        "limit_max": 4,
                        "limit_destination": "error/user_busy",
                        "call_timeout": 30,
                        "call_screen_enabled": "true",
                        "hold_music": null,
                        "nibble_account": null,
                        "sip_force_expires": null,
                        "mwi_account": "lwitting@yahoo.com",
                        "unique_id": null,
                        "dial_string": "/location/of/the/endpoint",
                        "dial_user": null,
                        "dial_domain": null,
                        "do_not_disturb": null,
                        "forward_all_destination": null,
                        "forward_all_enabled": null,
                        "forward_busy_destination": null,
                        "forward_busy_enabled": null,
                        "forward_no_answer_destination": null,
                        "forward_no_answer_enabled": null,
                        "forward_user_not_registered_destination": null,
                        "forward_user_not_registered_enabled": null,
                        "follow_me_uuid": null,
                        "enabled": "false",
                        "forward_caller_id_uuid": null,
                        "absolute_codec_string": "absolute/codec/string",
                        "extension": 169,
                        "password": "somePass1",
                        "accountcode": "account-8364",
                        "effective_caller_id_name": "William Reichel",
                        "effective_caller_id_number": 141,
                        "outbound_caller_id_name": "Lelia Wolff",
                        "outbound_caller_id_number": 120,
                        "emergency_caller_id_name": "Dr. Darrel Tillman",
                        "emergency_caller_id_number": 180,
                        "directory_first_name": "Mr. Carmine Becker",
                        "directory_last_name": "Pollich",
                        "missed_call_app": "string",
                        "missed_call_data": "string",
                        "toll_allow": "international",
                        "call_group": "billing",
                        "user_record": "all",
                        "auth_acl": "string",
                        "cidr": "string",
                        "sip_force_contact": "NDLB-tls-connectile-dysfunction",
                        "sip_bypass_media": "bypass-media",
                        "follow_me_enabled": "string",
                        "follow_me_destinations": "string",
                        "description": "Extension created while testing API",
                        "force_ping": "false",
                        "voicemail_password": 11097,
                        "greeting_id": 0,
                        "voicemail_alternate_greet_id": 0,
                        "voicemail_mail_to": "allene.koss@yahoo.com",
                        "voicemail_sms_to": "+1-992-616-7520",
                        "voicemail_transcription_enabled": "false",
                        "voicemail_attach_file": "/path/to/file",
                        "voicemail_file": "attach",
                        "voicemail_local_after_email": "false",
                        "voicemail_enabled": "true",
                        "voicemail_description": "Modi eligendi inventore hic numquam quia ut. Repellendus nostrum earum id. Consequuntur non dolor quos sit eos in facere.",
                        "voicemail_tutorial": "string"
                    },
                    {
                        "directory_visible": "true",
                        "directory_exten_visible": "true",
                        "limit_max": 5,
                        "limit_destination": "error/user_busy",
                        "call_timeout": 30,
                        "call_screen_enabled": "true",
                        "hold_music": null,
                        "nibble_account": null,
                        "sip_force_expires": null,
                        "mwi_account": "xondricka@hammes.org",
                        "unique_id": null,
                        "dial_string": "/location/of/the/endpoint",
                        "dial_user": null,
                        "dial_domain": null,
                        "do_not_disturb": null,
                        "forward_all_destination": null,
                        "forward_all_enabled": null,
                        "forward_busy_destination": null,
                        "forward_busy_enabled": null,
                        "forward_no_answer_destination": null,
                        "forward_no_answer_enabled": null,
                        "forward_user_not_registered_destination": null,
                        "forward_user_not_registered_enabled": null,
                        "follow_me_uuid": null,
                        "enabled": "false",
                        "forward_caller_id_uuid": null,
                        "absolute_codec_string": "absolute/codec/string",
                        "extension": 156,
                        "password": "somePass1",
                        "accountcode": "account-4644",
                        "effective_caller_id_name": "Mr. Albin Shields",
                        "effective_caller_id_number": 149,
                        "outbound_caller_id_name": "Oda Muller I",
                        "outbound_caller_id_number": 112,
                        "emergency_caller_id_name": "Felipa Kilback",
                        "emergency_caller_id_number": 108,
                        "directory_first_name": "Lonie Olson",
                        "directory_last_name": "Yost",
                        "missed_call_app": "string",
                        "missed_call_data": "string",
                        "toll_allow": "domestic",
                        "call_group": "billing",
                        "user_record": "all",
                        "auth_acl": "string",
                        "cidr": "string",
                        "sip_force_contact": "NDLB-connectile-dysfunction",
                        "sip_bypass_media": "bypass-media",
                        "follow_me_enabled": "string",
                        "follow_me_destinations": "string",
                        "description": "Extension created while testing API",
                        "force_ping": "true",
                        "voicemail_password": 63773,
                        "greeting_id": 0,
                        "voicemail_alternate_greet_id": 0,
                        "voicemail_mail_to": "garrison.brown@hotmail.com",
                        "voicemail_sms_to": "1-937-506-8698",
                        "voicemail_transcription_enabled": "true",
                        "voicemail_attach_file": "/path/to/file",
                        "voicemail_file": null,
                        "voicemail_local_after_email": "false",
                        "voicemail_enabled": "false",
                        "voicemail_description": "Aut cupiditate voluptatem dolorem vel et. Sequi eaque vel excepturi culpa minus similique. Optio quidem enim in mollitia dolores et rem itaque. Rerum cum reiciendis omnis sed dicta est.",
                        "voicemail_tutorial": "string"
                    }
                ]
            },
            {
                "is_admin": false,
                "username": "jazlyn.hoppe@nitzsche.com",
                "password": ".Apanter222",
                "user_email": "jazlyn.hoppe@nitzsche.com",
                "contacts": [
                    {
                        "contact_type": "volunteer",
                        "contact_organization": "Moore-Wisozk",
                        "contact_name_prefix": "Miss",
                        "contact_name_given": "Santa",
                        "contact_name_middle": "A.",
                        "contact_name_family": "Rice",
                        "contact_name_suffix": "DVM",
                        "contact_nickname": "ebailey",
                        "contact_title": "Dr.",
                        "contact_role": "TSA",
                        "contact_category": "Contacts added via API",
                        "contact_url": "http://www.mosciski.biz/laudantium-officia-eum-qui-et-quas-et",
                        "contact_time_zone": "Asia/Manila",
                        "contact_note": "Accusamus recusandae ipsa molestias. Amet voluptatum tempora nesciunt atque quasi."
                    },
                    {
                        "contact_type": "customer",
                        "contact_organization": "Watsica-Bradtke",
                        "contact_name_prefix": "Ms.",
                        "contact_name_given": "Manley",
                        "contact_name_middle": "A.",
                        "contact_name_family": "Weissnat",
                        "contact_name_suffix": "Jr.",
                        "contact_nickname": "harvey.ofelia",
                        "contact_title": "Prof.",
                        "contact_role": "Calibration Technician OR Instrumentation Technician",
                        "contact_category": "Contacts added via API",
                        "contact_url": "http://gusikowski.biz/debitis-maxime-quasi-atque.html",
                        "contact_time_zone": "America/Barbados",
                        "contact_note": "Dolor quos tenetur ut rerum quis nisi omnis. Aut blanditiis facere itaque qui temporibus porro. Id ut amet ad eos repellendus corporis."
                    }
                ],
                "extensions": [
                    {
                        "directory_visible": "true",
                        "directory_exten_visible": "true",
                        "limit_max": 2,
                        "limit_destination": "error/user_busy",
                        "call_timeout": 30,
                        "call_screen_enabled": "true",
                        "hold_music": "local_stream://default",
                        "nibble_account": null,
                        "sip_force_expires": null,
                        "mwi_account": "patrick.kerluke@gmail.com",
                        "unique_id": null,
                        "dial_string": "/location/of/the/endpoint",
                        "dial_user": null,
                        "dial_domain": null,
                        "do_not_disturb": null,
                        "forward_all_destination": null,
                        "forward_all_enabled": null,
                        "forward_busy_destination": null,
                        "forward_busy_enabled": null,
                        "forward_no_answer_destination": null,
                        "forward_no_answer_enabled": null,
                        "forward_user_not_registered_destination": null,
                        "forward_user_not_registered_enabled": null,
                        "follow_me_uuid": null,
                        "enabled": "true",
                        "forward_caller_id_uuid": null,
                        "absolute_codec_string": "absolute/codec/string",
                        "extension": 171,
                        "password": "asomePass1",
                        "accountcode": "account-9937",
                        "effective_caller_id_name": "Amanda Goldner",
                        "effective_caller_id_number": 145,
                        "outbound_caller_id_name": "Maximilian Heathcote",
                        "outbound_caller_id_number": 148,
                        "emergency_caller_id_name": "Norris Collier",
                        "emergency_caller_id_number": 128,
                        "directory_first_name": "Arianna Zieme",
                        "directory_last_name": "Hahn",
                        "missed_call_app": "string",
                        "missed_call_data": "string",
                        "toll_allow": "international",
                        "call_group": "billing",
                        "user_record": null,
                        "auth_acl": "string",
                        "cidr": "string",
                        "sip_force_contact": null,
                        "sip_bypass_media": "bypass-media-after-bridge",
                        "follow_me_enabled": "string",
                        "follow_me_destinations": "string",
                        "description": "Extension created while testing API",
                        "force_ping": "false",
                        "voicemail_password": 38837,
                        "greeting_id": 0,
                        "voicemail_alternate_greet_id": 0,
                        "voicemail_mail_to": "cathrine.dach@hessel.com",
                        "voicemail_sms_to": "+1 (306) 761-8344",
                        "voicemail_transcription_enabled": "true",
                        "voicemail_attach_file": "/path/to/file",
                        "voicemail_file": "attach",
                        "voicemail_local_after_email": "true",
                        "voicemail_enabled": "true",
                        "voicemail_description": "Ut ullam molestiae accusantium repellendus et. Quia aliquam quisquam corrupti mollitia commodi aperiam. Illum a aliquam quibusdam et eum.",
                        "voicemail_tutorial": "string"
                    },
                    {
                        "directory_visible": "true",
                        "directory_exten_visible": "false",
                        "limit_max": 6,
                        "limit_destination": "error/user_busy",
                        "call_timeout": 30,
                        "call_screen_enabled": "false",
                        "hold_music": "local_stream://default",
                        "nibble_account": null,
                        "sip_force_expires": null,
                        "mwi_account": "ferne.torphy@yahoo.com",
                        "unique_id": null,
                        "dial_string": "/location/of/the/endpoint",
                        "dial_user": null,
                        "dial_domain": null,
                        "do_not_disturb": null,
                        "forward_all_destination": null,
                        "forward_all_enabled": null,
                        "forward_busy_destination": null,
                        "forward_busy_enabled": null,
                        "forward_no_answer_destination": null,
                        "forward_no_answer_enabled": null,
                        "forward_user_not_registered_destination": null,
                        "forward_user_not_registered_enabled": null,
                        "follow_me_uuid": null,
                        "enabled": "false",
                        "forward_caller_id_uuid": null,
                        "absolute_codec_string": "absolute/codec/string",
                        "extension": 164,
                        "password": "somePass1",
                        "accountcode": "account-6963",
                        "effective_caller_id_name": "Joelle Rodriguez",
                        "effective_caller_id_number": 144,
                        "outbound_caller_id_name": "Otis Shields",
                        "outbound_caller_id_number": 144,
                        "emergency_caller_id_name": "Ahmad Muller",
                        "emergency_caller_id_number": 172,
                        "directory_first_name": "D'angelo Dach Sr.",
                        "directory_last_name": "Walker",
                        "missed_call_app": "string",
                        "missed_call_data": "string",
                        "toll_allow": "international",
                        "call_group": "billing",
                        "user_record": "local",
                        "auth_acl": "string",
                        "cidr": "string",
                        "sip_force_contact": "NDLB-connectile-dysfunction-2.0",
                        "sip_bypass_media": null,
                        "follow_me_enabled": "string",
                        "follow_me_destinations": "string",
                        "description": "Extension created while testing API",
                        "force_ping": "true",
                        "voicemail_password": 90705,
                        "greeting_id": 0,
                        "voicemail_alternate_greet_id": 0,
                        "voicemail_mail_to": "ctorp@gutkowski.com",
                        "voicemail_sms_to": "1-292-343-1434",
                        "voicemail_transcription_enabled": "true",
                        "voicemail_attach_file": "/path/to/file",
                        "voicemail_file": "attach",
                        "voicemail_local_after_email": "false",
                        "voicemail_enabled": "true",
                        "voicemail_description": "Laborum ut et consequuntur quaerat. Aut ut et dolor veritatis nihil laudantium. Nobis maxime non quas quidem assumenda. Consequuntur temporibus debitis molestias delectus animi non omnis.",
                        "voicemail_tutorial": "string"
                    }
                ]
            },
            {
                "is_admin": true,
                "reseller_reference_code": "Code03",
                "username": "marisa36@watsica.net",
                "password": "!uiS:9:",
                "user_email": "marisa36@watsica.net",
                "contacts": [
                    {
                        "contact_type": "supplier",
                        "contact_organization": "Carter, DuBuque and Lehner",
                        "contact_name_prefix": "Ms.",
                        "contact_name_given": "Ezekiel",
                        "contact_name_middle": "A.",
                        "contact_name_family": "Reilly",
                        "contact_name_suffix": "III",
                        "contact_nickname": "scotty.davis",
                        "contact_title": "Mrs.",
                        "contact_role": "Arbitrator",
                        "contact_category": "Contacts added via API",
                        "contact_url": "http://morar.com/",
                        "contact_time_zone": "Pacific/Tahiti",
                        "contact_note": "Ea placeat consequatur et repellendus mollitia nihil totam. Quam est enim vel perspiciatis."
                    },
                    {
                        "contact_type": "subscriber",
                        "contact_organization": "Farrell, Spinka and Conn",
                        "contact_name_prefix": "Ms.",
                        "contact_name_given": "Guiseppe",
                        "contact_name_middle": "A.",
                        "contact_name_family": "Gleichner",
                        "contact_name_suffix": "DDS",
                        "contact_nickname": "ashly32",
                        "contact_title": "Dr.",
                        "contact_role": "Aviation Inspector",
                        "contact_category": "Contacts added via API",
                        "contact_url": "http://feeney.biz/",
                        "contact_time_zone": "Asia/Novosibirsk",
                        "contact_note": "Ipsa asperiores ut vitae nobis qui. Vitae praesentium aut nobis et. Perspiciatis excepturi porro dolorem eaque magnam."
                    }
                ],
                "extensions": [
                    {
                        "directory_visible": "false",
                        "directory_exten_visible": "true",
                        "limit_max": 2,
                        "limit_destination": "error/user_busy",
                        "call_timeout": 30,
                        "call_screen_enabled": "true",
                        "hold_music": null,
                        "nibble_account": null,
                        "sip_force_expires": null,
                        "mwi_account": "herminio94@keebler.com",
                        "unique_id": null,
                        "dial_string": "/location/of/the/endpoint",
                        "dial_user": null,
                        "dial_domain": null,
                        "do_not_disturb": null,
                        "forward_all_destination": null,
                        "forward_all_enabled": null,
                        "forward_busy_destination": null,
                        "forward_busy_enabled": null,
                        "forward_no_answer_destination": null,
                        "forward_no_answer_enabled": null,
                        "forward_user_not_registered_destination": null,
                        "forward_user_not_registered_enabled": null,
                        "follow_me_uuid": null,
                        "enabled": "false",
                        "forward_caller_id_uuid": null,
                        "absolute_codec_string": "absolute/codec/string",
                        "extension": 172,
                        "password": "somePass1",
                        "accountcode": "account-4676",
                        "effective_caller_id_name": "Dario Hammes",
                        "effective_caller_id_number": 157,
                        "outbound_caller_id_name": "Abraham Heller",
                        "outbound_caller_id_number": 169,
                        "emergency_caller_id_name": "Mireya Will",
                        "emergency_caller_id_number": 114,
                        "directory_first_name": "Alvena Lemke",
                        "directory_last_name": "Will",
                        "missed_call_app": "string",
                        "missed_call_data": "string",
                        "toll_allow": "local",
                        "call_group": "sales",
                        "user_record": "all",
                        "auth_acl": "string",
                        "cidr": "string",
                        "sip_force_contact": "NDLB-connectile-dysfunction",
                        "sip_bypass_media": "bypass-media-after-bridge",
                        "follow_me_enabled": "string",
                        "follow_me_destinations": "string",
                        "description": "Extension created while testing API",
                        "force_ping": "true",
                        "voicemail_password": 14337,
                        "greeting_id": 0,
                        "voicemail_alternate_greet_id": 0,
                        "voicemail_mail_to": "shemar.steuber@runolfsdottir.com",
                        "voicemail_sms_to": "+1 (906) 407-0690",
                        "voicemail_transcription_enabled": "true",
                        "voicemail_attach_file": "/path/to/file",
                        "voicemail_file": null,
                        "voicemail_local_after_email": "false",
                        "voicemail_enabled": "false",
                        "voicemail_description": "Deserunt distinctio iusto omnis qui debitis. Enim itaque est omnis illo id debitis. Saepe sit eligendi corporis et. Exercitationem quis ullam illum sed.",
                        "voicemail_tutorial": "string"
                    },
                    {
                        "directory_visible": "true",
                        "directory_exten_visible": "false",
                        "limit_max": 7,
                        "limit_destination": "error/user_busy",
                        "call_timeout": 30,
                        "call_screen_enabled": "false",
                        "hold_music": "local_stream://default",
                        "nibble_account": null,
                        "sip_force_expires": null,
                        "mwi_account": "mpfeffer@metz.com",
                        "unique_id": null,
                        "dial_string": "/location/of/the/endpoint",
                        "dial_user": null,
                        "dial_domain": null,
                        "do_not_disturb": null,
                        "forward_all_destination": null,
                        "forward_all_enabled": null,
                        "forward_busy_destination": null,
                        "forward_busy_enabled": null,
                        "forward_no_answer_destination": null,
                        "forward_no_answer_enabled": null,
                        "forward_user_not_registered_destination": null,
                        "forward_user_not_registered_enabled": null,
                        "follow_me_uuid": null,
                        "enabled": "true",
                        "forward_caller_id_uuid": null,
                        "absolute_codec_string": "absolute/codec/string",
                        "extension": 123,
                        "password": "somePass1",
                        "accountcode": "account-3558",
                        "effective_caller_id_name": "Mateo Abernathy",
                        "effective_caller_id_number": 174,
                        "outbound_caller_id_name": "Dr. Haylee Bartoletti Jr.",
                        "outbound_caller_id_number": 195,
                        "emergency_caller_id_name": "Virginie Waelchi",
                        "emergency_caller_id_number": 200,
                        "directory_first_name": "Romaine Mayer Sr.",
                        "directory_last_name": "Lowe",
                        "missed_call_app": "string",
                        "missed_call_data": "string",
                        "toll_allow": "local",
                        "call_group": "sales",
                        "user_record": "outbound",
                        "auth_acl": "string",
                        "cidr": "string",
                        "sip_force_contact": "NDLB-tls-connectile-dysfunction",
                        "sip_bypass_media": "proxy-media",
                        "follow_me_enabled": "string",
                        "follow_me_destinations": "string",
                        "description": "Extension created while testing API",
                        "force_ping": null,
                        "voicemail_password": 34130,
                        "greeting_id": 0,
                        "voicemail_alternate_greet_id": 0,
                        "voicemail_mail_to": "virginia.sauer@yahoo.com",
                        "voicemail_sms_to": "1-475-877-2613",
                        "voicemail_transcription_enabled": "false",
                        "voicemail_attach_file": "/path/to/file",
                        "voicemail_file": null,
                        "voicemail_local_after_email": "false",
                        "voicemail_enabled": "false",
                        "voicemail_description": "Iusto sint ex est delectus ut. Qui facere cum omnis ducimus nisi. Ab omnis itaque vitae perspiciatis. Omnis repellat delectus et at dolor expedita voluptas.",
                        "voicemail_tutorial": "string"
                    }
                ]
            }
        ]
    },
    "updated_at": "2021-08-23T19:12:52.000000Z",
    "created_at": "2021-08-23T19:12:52.000000Z"
}
